<?xml version="1.0" encoding="utf-8"?>
<SoundBanksInfo Platform="Windows" BasePlatform="Windows" SchemaVersion="16" SoundBankVersion="145">
	<RootPaths>
		<ProjectRoot>../..</ProjectRoot>
		<SourceFilesRoot>../../.cache/Windows</SourceFilesRoot>
		<SoundBanksRoot>.</SoundBanksRoot>
		<ExternalSourcesInputFile></ExternalSourcesInputFile>
		<ExternalSourcesOutputRoot>.</ExternalSourcesOutputRoot>
	</RootPaths>
	<DialogueEvents/>
	<SoundBanks>
		<SoundBank Id="534561221" Type="User" Language="SFX" Hash="{09CC0EB7-8395-F46D-4ABB-E2C622290D4B}">
			<ShortName>MainSoundBank</ShortName>
			<Path>MainSoundBank.bnk</Path>
			<Media>
				<File Id="136212208" Language="SFX" Streaming="false" Location="Memory">
					<ShortName>77245__studiocopsey__power-up.wav</ShortName>
					<CachePath>SFX/77245__studiocopsey__power-up_7E948A5A.wem</CachePath>
				</File>
				<File Id="306663159" Language="SFX" Streaming="false" Location="Memory">
					<ShortName>77245__studiocopsey__power-up.wav</ShortName>
					<CachePath>SFX/77245__studiocopsey__power-up_3F121601.wem</CachePath>
				</File>
				<File Id="529159546" Language="SFX" Streaming="false" Location="Memory">
					<ShortName>Explosion8bit.wav</ShortName>
					<CachePath>SFX/Explosion8bit_3941A393.wem</CachePath>
				</File>
			</Media>
			<Plugins>
				<Custom>
					<Plugin Id="542053558" Name="Monsterize (Custom)" LibName="Wwise Pitch Shifter" LibId="8912899"/>
				</Custom>
				<ShareSets>
					<Plugin Id="654807232" Name="Chipmunk" LibName="Wwise Pitch Shifter" LibId="8912899"/>
					<Plugin Id="1588715066" Name="Echoes_Linear" LibName="Wwise Delay" LibId="6946819"/>
				</ShareSets>
			</Plugins>
			<Events>
				<Event Id="1205999388" Name="Enemy_Death" MaxAttenuation="15" DurationType="OneShot" DurationMin="0.085381195" DurationMax="0.24771082">
					<MediaRefs>
						<MediaRef Id="529159546"/>
					</MediaRefs>
					<PluginRefs>
						<ShareSets>
							<PluginRef Id="654807232"/>
							<PluginRef Id="1588715066"/>
						</ShareSets>
					</PluginRefs>
				</Event>
				<Event Id="1598016745" Name="Play_XP_PickUp" DurationType="OneShot" DurationMin="0.12755391" DurationMax="0.28045586">
					<MediaRefs>
						<MediaRef Id="306663159"/>
					</MediaRefs>
				</Event>
				<Event Id="4191302951" Name="Shot_MachineGun" DurationType="OneShot" DurationMin="0.10156628" DurationMax="0.10156628">
					<MediaRefs>
						<MediaRef Id="136212208"/>
					</MediaRefs>
					<PluginRefs>
						<Custom>
							<PluginRef Id="542053558"/>
						</Custom>
					</PluginRefs>
				</Event>
			</Events>
		</SoundBank>
		<SoundBank Id="1355168291" Type="User" Language="SFX" Hash="{60CCBE60-46C2-91C5-3191-3BA7E161D2FC}">
			<ShortName>Init</ShortName>
			<Path>Init.bnk</Path>
			<Plugins>
				<AudioDevices>
					<Plugin Id="2317455096" Name="No_Output" LibName="No Output" LibId="11862023"/>
					<Plugin Id="3859886410" Name="System" LibName="System" LibId="11403271"/>
				</AudioDevices>
			</Plugins>
			<Busses>
				<Bus Id="3803692087" Name="Master Audio Bus"/>
			</Busses>
		</SoundBank>
	</SoundBanks>
	<FileHash>{E7B91EDE-9E1C-F32F-75EC-35A9F2398C2C}</FileHash>
</SoundBanksInfo>
